shappack/__init__.py
shappack/logging.py
shappack/characteristic_funcs/__init__.py
shappack/characteristic_funcs/reference.py
shappack/explainers/__init__.py
shappack/explainers/_base.py
shappack/explainers/_kernel.py
shappack/explainers/base.py
shappack/explainers/kernel.py
shappack/utils/__init__.py
shappack/utils/_link.py
shappack/utils/docker.py
shappack/utils/link.py
tests/characteristic_funcs/__init__.py
tests/characteristic_funcs/test_reference.py
tests/explainers/__init__.py
tests/explainers/test_kernel.py
shappack-0.1.1.dist-info/LICENSE
shappack-0.1.1.dist-info/METADATA
shappack-0.1.1.dist-info/WHEEL
shappack-0.1.1.dist-info/top_level.txt
shappack-0.1.1.dist-info/RECORD
