Metadata-Version: 2.1
Name: shappack
Version: 0.1.1
Summary: Interpretable machine learning based on Shapley values
Home-page: UNKNOWN
Author: Hirofumi Tsuruta
License: UNKNOWN
Platform: UNKNOWN
Requires-Dist: numpy
Requires-Dist: pandas
Requires-Dist: sklearn
Requires-Dist: scipy
Provides-Extra: dev
Requires-Dist: black ; extra == 'dev'
Requires-Dist: pytest ; extra == 'dev'
Requires-Dist: wheel ; extra == 'dev'
Requires-Dist: twine ; extra == 'dev'
Requires-Dist: shap ; extra == 'dev'
Requires-Dist: matplotlib ; extra == 'dev'
Requires-Dist: jupyterlab ; extra == 'dev'
Provides-Extra: test
Requires-Dist: black ; extra == 'test'
Requires-Dist: pytest ; extra == 'test'
